{"config":{"output_file":null,"full_docs":false,"pub_only":false,"reachable_only":false,"distro_crate":false,"signatures":false,"borrow_data":false},"version":"0.19.1","compilation":{"directory":"c:\\Users\\комфи\\Documents\\Near\\purgatory\\contracts\\token","program":"C:\\Users\\комфи\\.rustup\\toolchains\\stable-x86_64-pc-windows-msvc\\bin\\rls.exe","arguments":[],"output":"c:\\Users\\комфи\\Documents\\Near\\purgatory\\contracts\\token\\target\\rls\\debug\\deps\\libnews_validator-3d78e040a2ee40bc.rmeta"},"prelude":{"crate_id":{"name":"news_validator","disambiguator":[9195758304309918382,0]},"crate_root":"src","external_crates":[{"file_name":"c:\\Users\\комфи\\Documents\\Near\\purgatory\\contracts\\token\\src\\lib.rs","num":1,"id":{"name":"std","disambiguator":[7976927198175868373,0]}},{"file_name":"c:\\Users\\комфи\\Documents\\Near\\purgatory\\contracts\\token\\src\\lib.rs","num":2,"id":{"name":"core","disambiguator":[11165144592143370822,0]}},{"file_name":"c:\\Users\\комфи\\Documents\\Near\\purgatory\\contracts\\token\\src\\lib.rs","num":3,"id":{"name":"compiler_builtins","disambiguator":[252041924521724887,0]}},{"file_name":"c:\\Users\\комфи\\Documents\\Near\\purgatory\\contracts\\token\\src\\lib.rs","num":4,"id":{"name":"rustc_std_workspace_core","disambiguator":[5467317383579905353,0]}},{"file_name":"c:\\Users\\комфи\\Documents\\Near\\purgatory\\contracts\\token\\src\\lib.rs","num":5,"id":{"name":"alloc","disambiguator":[7624884120048857693,0]}},{"file_name":"c:\\Users\\комфи\\Documents\\Near\\purgatory\\contracts\\token\\src\\lib.rs","num":6,"id":{"name":"libc","disambiguator":[11703982264691436790,0]}},{"file_name":"c:\\Users\\комфи\\Documents\\Near\\purgatory\\contracts\\token\\src\\lib.rs","num":7,"id":{"name":"unwind","disambiguator":[2970152443746782806,0]}},{"file_name":"c:\\Users\\комфи\\Documents\\Near\\purgatory\\contracts\\token\\src\\lib.rs","num":8,"id":{"name":"cfg_if","disambiguator":[9222488229097456044,0]}},{"file_name":"c:\\Users\\комфи\\Documents\\Near\\purgatory\\contracts\\token\\src\\lib.rs","num":9,"id":{"name":"hashbrown","disambiguator":[7853498759631503325,0]}},{"file_name":"c:\\Users\\комфи\\Documents\\Near\\purgatory\\contracts\\token\\src\\lib.rs","num":10,"id":{"name":"rustc_std_workspace_alloc","disambiguator":[16147963203778103955,0]}},{"file_name":"c:\\Users\\комфи\\Documents\\Near\\purgatory\\contracts\\token\\src\\lib.rs","num":11,"id":{"name":"rustc_demangle","disambiguator":[14622278557065309757,0]}},{"file_name":"c:\\Users\\комфи\\Documents\\Near\\purgatory\\contracts\\token\\src\\lib.rs","num":12,"id":{"name":"std_detect","disambiguator":[12620427935833221912,0]}},{"file_name":"c:\\Users\\комфи\\Documents\\Near\\purgatory\\contracts\\token\\src\\lib.rs","num":13,"id":{"name":"panic_unwind","disambiguator":[5227252993197737239,0]}},{"file_name":"c:\\Users\\комфи\\Documents\\Near\\purgatory\\contracts\\token\\src\\lib.rs","num":14,"id":{"name":"near_contract_standards","disambiguator":[11492597541821712419,0]}},{"file_name":"c:\\Users\\комфи\\Documents\\Near\\purgatory\\contracts\\token\\src\\lib.rs","num":15,"id":{"name":"near_sdk","disambiguator":[17498585613224193912,0]}},{"file_name":"c:\\Users\\комфи\\Documents\\Near\\purgatory\\contracts\\token\\src\\lib.rs","num":16,"id":{"name":"near_sdk_macros","disambiguator":[11899943523627577549,0]}},{"file_name":"c:\\Users\\комфи\\Documents\\Near\\purgatory\\contracts\\token\\src\\lib.rs","num":17,"id":{"name":"borsh","disambiguator":[9067488601933251079,0]}},{"file_name":"c:\\Users\\комфи\\Documents\\Near\\purgatory\\contracts\\token\\src\\lib.rs","num":18,"id":{"name":"borsh_derive","disambiguator":[6844026864700459600,0]}},{"file_name":"c:\\Users\\комфи\\Documents\\Near\\purgatory\\contracts\\token\\src\\lib.rs","num":19,"id":{"name":"near_vm_logic","disambiguator":[5569856652397503654,0]}},{"file_name":"c:\\Users\\комфи\\Documents\\Near\\purgatory\\contracts\\token\\src\\lib.rs","num":20,"id":{"name":"serde","disambiguator":[6389045921535102661,0]}},{"file_name":"c:\\Users\\комфи\\Documents\\Near\\purgatory\\contracts\\token\\src\\lib.rs","num":21,"id":{"name":"serde_derive","disambiguator":[12524280473244481901,0]}},{"file_name":"c:\\Users\\комфи\\Documents\\Near\\purgatory\\contracts\\token\\src\\lib.rs","num":22,"id":{"name":"near_primitives_core","disambiguator":[286196532410413459,0]}},{"file_name":"c:\\Users\\комфи\\Documents\\Near\\purgatory\\contracts\\token\\src\\lib.rs","num":23,"id":{"name":"num_rational","disambiguator":[13905569804666340534,0]}},{"file_name":"c:\\Users\\комфи\\Documents\\Near\\purgatory\\contracts\\token\\src\\lib.rs","num":24,"id":{"name":"num_bigint","disambiguator":[9721697701201561399,0]}},{"file_name":"c:\\Users\\комфи\\Documents\\Near\\purgatory\\contracts\\token\\src\\lib.rs","num":25,"id":{"name":"num_integer","disambiguator":[2168420133138146619,0]}},{"file_name":"c:\\Users\\комфи\\Documents\\Near\\purgatory\\contracts\\token\\src\\lib.rs","num":26,"id":{"name":"num_traits","disambiguator":[12228964905765682762,0]}},{"file_name":"c:\\Users\\комфи\\Documents\\Near\\purgatory\\contracts\\token\\src\\lib.rs","num":27,"id":{"name":"sha2","disambiguator":[4333900173693407578,0]}},{"file_name":"c:\\Users\\комфи\\Documents\\Near\\purgatory\\contracts\\token\\src\\lib.rs","num":28,"id":{"name":"block_buffer","disambiguator":[1916395949302749190,0]}},{"file_name":"c:\\Users\\комфи\\Documents\\Near\\purgatory\\contracts\\token\\src\\lib.rs","num":29,"id":{"name":"generic_array","disambiguator":[11441046755003778619,0]}},{"file_name":"c:\\Users\\комфи\\Documents\\Near\\purgatory\\contracts\\token\\src\\lib.rs","num":30,"id":{"name":"typenum","disambiguator":[1960753495786202881,0]}},{"file_name":"c:\\Users\\комфи\\Documents\\Near\\purgatory\\contracts\\token\\src\\lib.rs","num":31,"id":{"name":"digest","disambiguator":[11318381085398126053,0]}},{"file_name":"c:\\Users\\комфи\\Documents\\Near\\purgatory\\contracts\\token\\src\\lib.rs","num":32,"id":{"name":"opaque_debug","disambiguator":[12470355041016524094,0]}},{"file_name":"c:\\Users\\комфи\\Documents\\Near\\purgatory\\contracts\\token\\src\\lib.rs","num":33,"id":{"name":"cfg_if","disambiguator":[12394071839129264589,0]}},{"file_name":"c:\\Users\\комфи\\Documents\\Near\\purgatory\\contracts\\token\\src\\lib.rs","num":34,"id":{"name":"cpuid_bool","disambiguator":[7497721718980875094,0]}},{"file_name":"c:\\Users\\комфи\\Documents\\Near\\purgatory\\contracts\\token\\src\\lib.rs","num":35,"id":{"name":"derive_more","disambiguator":[10697986762395726342,0]}},{"file_name":"c:\\Users\\комфи\\Documents\\Near\\purgatory\\contracts\\token\\src\\lib.rs","num":36,"id":{"name":"bs58","disambiguator":[4471029787260119554,0]}},{"file_name":"c:\\Users\\комфи\\Documents\\Near\\purgatory\\contracts\\token\\src\\lib.rs","num":37,"id":{"name":"base64","disambiguator":[15050966374503021954,0]}},{"file_name":"c:\\Users\\комфи\\Documents\\Near\\purgatory\\contracts\\token\\src\\lib.rs","num":38,"id":{"name":"near_vm_errors","disambiguator":[15041480736508924086,0]}},{"file_name":"c:\\Users\\комфи\\Documents\\Near\\purgatory\\contracts\\token\\src\\lib.rs","num":39,"id":{"name":"near_rpc_error_macro","disambiguator":[8283266582999424897,0]}},{"file_name":"c:\\Users\\комфи\\Documents\\Near\\purgatory\\contracts\\token\\src\\lib.rs","num":40,"id":{"name":"hex","disambiguator":[10194816230867959960,0]}},{"file_name":"c:\\Users\\комфи\\Documents\\Near\\purgatory\\contracts\\token\\src\\lib.rs","num":41,"id":{"name":"byteorder","disambiguator":[3306298670580596047,0]}},{"file_name":"c:\\Users\\комфи\\Documents\\Near\\purgatory\\contracts\\token\\src\\lib.rs","num":42,"id":{"name":"near_runtime_utils","disambiguator":[9611952200236579291,0]}},{"file_name":"c:\\Users\\комфи\\Documents\\Near\\purgatory\\contracts\\token\\src\\lib.rs","num":43,"id":{"name":"lazy_static","disambiguator":[8441177590269360409,0]}},{"file_name":"c:\\Users\\комфи\\Documents\\Near\\purgatory\\contracts\\token\\src\\lib.rs","num":44,"id":{"name":"regex","disambiguator":[15506617253535119988,0]}},{"file_name":"c:\\Users\\комфи\\Documents\\Near\\purgatory\\contracts\\token\\src\\lib.rs","num":45,"id":{"name":"aho_corasick","disambiguator":[2239850450382298064,0]}},{"file_name":"c:\\Users\\комфи\\Documents\\Near\\purgatory\\contracts\\token\\src\\lib.rs","num":46,"id":{"name":"memchr","disambiguator":[3683775589952850736,0]}},{"file_name":"c:\\Users\\комфи\\Documents\\Near\\purgatory\\contracts\\token\\src\\lib.rs","num":47,"id":{"name":"regex_syntax","disambiguator":[10504087048903737152,0]}},{"file_name":"c:\\Users\\комфи\\Documents\\Near\\purgatory\\contracts\\token\\src\\lib.rs","num":48,"id":{"name":"sha3","disambiguator":[5000851970463334969,0]}},{"file_name":"c:\\Users\\комфи\\Documents\\Near\\purgatory\\contracts\\token\\src\\lib.rs","num":49,"id":{"name":"keccak","disambiguator":[4564083808443519386,0]}},{"file_name":"c:\\Users\\комфи\\Documents\\Near\\purgatory\\contracts\\token\\src\\lib.rs","num":50,"id":{"name":"block_buffer","disambiguator":[3253820964402209523,0]}},{"file_name":"c:\\Users\\комфи\\Documents\\Near\\purgatory\\contracts\\token\\src\\lib.rs","num":51,"id":{"name":"block_padding","disambiguator":[1414753540362560895,0]}},{"file_name":"c:\\Users\\комфи\\Documents\\Near\\purgatory\\contracts\\token\\src\\lib.rs","num":52,"id":{"name":"byte_tools","disambiguator":[8009720836280638797,0]}},{"file_name":"c:\\Users\\комфи\\Documents\\Near\\purgatory\\contracts\\token\\src\\lib.rs","num":53,"id":{"name":"generic_array","disambiguator":[15546416394745896530,0]}},{"file_name":"c:\\Users\\комфи\\Documents\\Near\\purgatory\\contracts\\token\\src\\lib.rs","num":54,"id":{"name":"opaque_debug","disambiguator":[926686147730698666,0]}},{"file_name":"c:\\Users\\комфи\\Documents\\Near\\purgatory\\contracts\\token\\src\\lib.rs","num":55,"id":{"name":"digest","disambiguator":[9508186809622443626,0]}},{"file_name":"c:\\Users\\комфи\\Documents\\Near\\purgatory\\contracts\\token\\src\\lib.rs","num":56,"id":{"name":"serde_json","disambiguator":[16218487423175659969,0]}},{"file_name":"c:\\Users\\комфи\\Documents\\Near\\purgatory\\contracts\\token\\src\\lib.rs","num":57,"id":{"name":"indexmap","disambiguator":[17436463539080930543,0]}},{"file_name":"c:\\Users\\комфи\\Documents\\Near\\purgatory\\contracts\\token\\src\\lib.rs","num":58,"id":{"name":"hashbrown","disambiguator":[7480016108753022708,0]}},{"file_name":"c:\\Users\\комфи\\Documents\\Near\\purgatory\\contracts\\token\\src\\lib.rs","num":59,"id":{"name":"itoa","disambiguator":[3265471860207340789,0]}},{"file_name":"c:\\Users\\комфи\\Documents\\Near\\purgatory\\contracts\\token\\src\\lib.rs","num":60,"id":{"name":"ryu","disambiguator":[1356372711632948565,0]}},{"file_name":"c:\\Users\\комфи\\Documents\\Near\\purgatory\\contracts\\token\\src\\lib.rs","num":61,"id":{"name":"wee_alloc","disambiguator":[573405404537047905,0]}},{"file_name":"c:\\Users\\комфи\\Documents\\Near\\purgatory\\contracts\\token\\src\\lib.rs","num":62,"id":{"name":"cfg_if","disambiguator":[2603666211785926936,0]}},{"file_name":"c:\\Users\\комфи\\Documents\\Near\\purgatory\\contracts\\token\\src\\lib.rs","num":63,"id":{"name":"memory_units","disambiguator":[12636767997866826069,0]}},{"file_name":"c:\\Users\\комфи\\Documents\\Near\\purgatory\\contracts\\token\\src\\lib.rs","num":64,"id":{"name":"winapi","disambiguator":[3002636915166710480,0]}},{"file_name":"c:\\Users\\комфи\\Documents\\Near\\purgatory\\contracts\\token\\src\\lib.rs","num":65,"id":{"name":"test","disambiguator":[9044787055298242909,0]}},{"file_name":"c:\\Users\\комфи\\Documents\\Near\\purgatory\\contracts\\token\\src\\lib.rs","num":66,"id":{"name":"getopts","disambiguator":[4597321755653536454,0]}},{"file_name":"c:\\Users\\комфи\\Documents\\Near\\purgatory\\contracts\\token\\src\\lib.rs","num":67,"id":{"name":"rustc_std_workspace_std","disambiguator":[9354194117945341218,0]}},{"file_name":"c:\\Users\\комфи\\Documents\\Near\\purgatory\\contracts\\token\\src\\lib.rs","num":68,"id":{"name":"unicode_width","disambiguator":[4740537085030749967,0]}}],"span":{"file_name":"src\\lib.rs","byte_start":0,"byte_end":688,"line_start":1,"line_end":16,"column_start":1,"column_end":26}},"imports":[{"kind":"Use","ref_id":{"krate":14,"index":1087},"span":{"file_name":"src\\lib.rs","byte_start":65,"byte_end":84,"line_start":2,"line_end":2,"column_start":5,"column_end":24},"alias_span":null,"name":"NFTContractMetadata","value":"","parent":{"krate":0,"index":0}},{"kind":"Use","ref_id":{"krate":14,"index":546},"span":{"file_name":"src\\lib.rs","byte_start":86,"byte_end":118,"line_start":2,"line_end":2,"column_start":26,"column_end":58},"alias_span":null,"name":"NonFungibleTokenMetadataProvider","value":"","parent":{"krate":0,"index":0}},{"kind":"Use","ref_id":{"krate":14,"index":1181},"span":{"file_name":"src\\lib.rs","byte_start":120,"byte_end":133,"line_start":2,"line_end":2,"column_start":60,"column_end":73},"alias_span":null,"name":"TokenMetadata","value":"","parent":{"krate":0,"index":0}},{"kind":"Use","ref_id":{"krate":14,"index":545},"span":{"file_name":"src\\lib.rs","byte_start":135,"byte_end":152,"line_start":2,"line_end":2,"column_start":75,"column_end":92},"alias_span":null,"name":"NFT_METADATA_SPEC","value":"","parent":{"krate":0,"index":0}},{"kind":"Use","ref_id":{"krate":14,"index":1259},"span":{"file_name":"src\\lib.rs","byte_start":207,"byte_end":212,"line_start":4,"line_end":4,"column_start":51,"column_end":56},"alias_span":null,"name":"Token","value":"","parent":{"krate":0,"index":0}},{"kind":"Use","ref_id":{"krate":14,"index":569},"span":{"file_name":"src\\lib.rs","byte_start":214,"byte_end":221,"line_start":4,"line_end":4,"column_start":58,"column_end":65},"alias_span":null,"name":"TokenId","value":"","parent":{"krate":0,"index":0}},{"kind":"Use","ref_id":{"krate":14,"index":989},"span":{"file_name":"src\\lib.rs","byte_start":273,"byte_end":289,"line_start":5,"line_end":5,"column_start":50,"column_end":66},"alias_span":null,"name":"NonFungibleToken","value":"","parent":{"krate":0,"index":0}},{"kind":"Use","ref_id":{"krate":17,"index":0},"span":{"file_name":"src\\lib.rs","byte_start":305,"byte_end":310,"line_start":6,"line_end":6,"column_start":15,"column_end":20},"alias_span":null,"name":"borsh","value":"","parent":{"krate":0,"index":0}},{"kind":"Use","ref_id":{"krate":17,"index":97},"span":{"file_name":"src\\lib.rs","byte_start":319,"byte_end":335,"line_start":6,"line_end":6,"column_start":29,"column_end":45},"alias_span":null,"name":"BorshDeserialize","value":"","parent":{"krate":0,"index":0}},{"kind":"Use","ref_id":{"krate":18,"index":29},"span":{"file_name":"src\\lib.rs","byte_start":319,"byte_end":335,"line_start":6,"line_end":6,"column_start":29,"column_end":45},"alias_span":null,"name":"BorshDeserialize","value":"","parent":{"krate":0,"index":0}},{"kind":"Use","ref_id":{"krate":17,"index":344},"span":{"file_name":"src\\lib.rs","byte_start":337,"byte_end":351,"line_start":6,"line_end":6,"column_start":47,"column_end":61},"alias_span":null,"name":"BorshSerialize","value":"","parent":{"krate":0,"index":0}},{"kind":"Use","ref_id":{"krate":18,"index":28},"span":{"file_name":"src\\lib.rs","byte_start":337,"byte_end":351,"line_start":6,"line_end":6,"column_start":47,"column_end":61},"alias_span":null,"name":"BorshSerialize","value":"","parent":{"krate":0,"index":0}},{"kind":"Use","ref_id":{"krate":15,"index":1693},"span":{"file_name":"src\\lib.rs","byte_start":381,"byte_end":391,"line_start":7,"line_end":7,"column_start":28,"column_end":38},"alias_span":null,"name":"LazyOption","value":"","parent":{"krate":0,"index":0}},{"kind":"Use","ref_id":{"krate":15,"index":1805},"span":{"file_name":"src\\lib.rs","byte_start":419,"byte_end":433,"line_start":8,"line_end":8,"column_start":27,"column_end":41},"alias_span":null,"name":"ValidAccountId","value":"","parent":{"krate":0,"index":0}},{"kind":"Use","ref_id":{"krate":15,"index":739},"span":{"file_name":"src\\lib.rs","byte_start":455,"byte_end":458,"line_start":10,"line_end":10,"column_start":5,"column_end":8},"alias_span":null,"name":"env","value":"","parent":{"krate":0,"index":0}},{"kind":"Use","ref_id":{"krate":16,"index":33},"span":{"file_name":"src\\lib.rs","byte_start":460,"byte_end":472,"line_start":10,"line_end":10,"column_start":10,"column_end":22},"alias_span":null,"name":"near_bindgen","value":"","parent":{"krate":0,"index":0}},{"kind":"Use","ref_id":{"krate":22,"index":514},"span":{"file_name":"src\\lib.rs","byte_start":474,"byte_end":483,"line_start":10,"line_end":10,"column_start":24,"column_end":33},"alias_span":null,"name":"AccountId","value":"","parent":{"krate":0,"index":0}},{"kind":"Use","ref_id":{"krate":16,"index":43},"span":{"file_name":"src\\lib.rs","byte_start":485,"byte_end":500,"line_start":10,"line_end":10,"column_start":35,"column_end":50},"alias_span":null,"name":"BorshStorageKey","value":"","parent":{"krate":0,"index":0}},{"kind":"Use","ref_id":{"krate":16,"index":42},"span":{"file_name":"src\\lib.rs","byte_start":502,"byte_end":516,"line_start":10,"line_end":10,"column_start":52,"column_end":66},"alias_span":null,"name":"PanicOnDefault","value":"","parent":{"krate":0,"index":0}},{"kind":"Use","ref_id":{"krate":15,"index":1746},"span":{"file_name":"src\\lib.rs","byte_start":518,"byte_end":525,"line_start":10,"line_end":10,"column_start":68,"column_end":75},"alias_span":null,"name":"Promise","value":"","parent":{"krate":0,"index":0}},{"kind":"Use","ref_id":{"krate":15,"index":1133},"span":{"file_name":"src\\lib.rs","byte_start":527,"byte_end":541,"line_start":10,"line_end":10,"column_start":77,"column_end":91},"alias_span":null,"name":"PromiseOrValue","value":"","parent":{"krate":0,"index":0}},{"kind":"Use","ref_id":{"krate":1,"index":1807},"span":{"file_name":"src\\lib.rs","byte_start":568,"byte_end":575,"line_start":12,"line_end":12,"column_start":23,"column_end":30},"alias_span":null,"name":"HashSet","value":"","parent":{"krate":0,"index":0}},{"kind":"Use","ref_id":{"krate":20,"index":1984},"span":{"file_name":"src\\lib.rs","byte_start":599,"byte_end":608,"line_start":13,"line_end":13,"column_start":23,"column_end":32},"alias_span":null,"name":"Serialize","value":"","parent":{"krate":0,"index":0}},{"kind":"Use","ref_id":{"krate":21,"index":1121},"span":{"file_name":"src\\lib.rs","byte_start":599,"byte_end":608,"line_start":13,"line_end":13,"column_start":23,"column_end":32},"alias_span":null,"name":"Serialize","value":"","parent":{"krate":0,"index":0}},{"kind":"Use","ref_id":{"krate":20,"index":1448},"span":{"file_name":"src\\lib.rs","byte_start":610,"byte_end":621,"line_start":13,"line_end":13,"column_start":34,"column_end":45},"alias_span":null,"name":"Deserialize","value":"","parent":{"krate":0,"index":0}},{"kind":"Use","ref_id":{"krate":21,"index":1122},"span":{"file_name":"src\\lib.rs","byte_start":610,"byte_end":621,"line_start":13,"line_end":13,"column_start":34,"column_end":45},"alias_span":null,"name":"Deserialize","value":"","parent":{"krate":0,"index":0}},{"kind":"Use","ref_id":{"krate":2,"index":2898},"span":{"file_name":"src\\lib.rs","byte_start":643,"byte_end":650,"line_start":14,"line_end":14,"column_start":20,"column_end":27},"alias_span":null,"name":"TryInto","value":"","parent":{"krate":0,"index":0}},{"kind":"Use","ref_id":{"krate":2,"index":2902},"span":{"file_name":"src\\lib.rs","byte_start":652,"byte_end":659,"line_start":14,"line_end":14,"column_start":29,"column_end":36},"alias_span":null,"name":"TryFrom","value":"","parent":{"krate":0,"index":0}}],"defs":[{"kind":"Mod","id":{"krate":0,"index":0},"span":{"file_name":"src\\lib.rs","byte_start":0,"byte_end":688,"line_start":1,"line_end":16,"column_start":1,"column_end":26},"name":"","qualname":"::","value":"src\\lib.rs","parent":null,"children":[{"krate":0,"index":1},{"krate":0,"index":2},{"krate":0,"index":3},{"krate":0,"index":4},{"krate":0,"index":7},{"krate":0,"index":10},{"krate":0,"index":13},{"krate":0,"index":16},{"krate":0,"index":17},{"krate":0,"index":20},{"krate":0,"index":23},{"krate":0,"index":26},{"krate":0,"index":27},{"krate":0,"index":30},{"krate":0,"index":31},{"krate":0,"index":33},{"krate":0,"index":34},{"krate":0,"index":36},{"krate":0,"index":39},{"krate":0,"index":42},{"krate":0,"index":43},{"krate":0,"index":46},{"krate":0,"index":49},{"krate":0,"index":52},{"krate":0,"index":55},{"krate":0,"index":58},{"krate":0,"index":61},{"krate":0,"index":64},{"krate":0,"index":67},{"krate":0,"index":68},{"krate":0,"index":69},{"krate":0,"index":71},{"krate":0,"index":72},{"krate":0,"index":74},{"krate":0,"index":75},{"krate":0,"index":78},{"krate":0,"index":81}],"decl_id":null,"docs":"","sig":null,"attributes":[]}],"impls":[],"refs":[{"kind":"Type","span":{"file_name":"src\\lib.rs","byte_start":4,"byte_end":27,"line_start":1,"line_end":1,"column_start":5,"column_end":28},"ref_id":{"krate":14,"index":1087}},{"kind":"Type","span":{"file_name":"src\\lib.rs","byte_start":29,"byte_end":47,"line_start":1,"line_end":1,"column_start":30,"column_end":48},"ref_id":{"krate":14,"index":1087}},{"kind":"Type","span":{"file_name":"src\\lib.rs","byte_start":49,"byte_end":57,"line_start":1,"line_end":1,"column_start":50,"column_end":58},"ref_id":{"krate":14,"index":1087}},{"kind":"Type","span":{"file_name":"src\\lib.rs","byte_start":4,"byte_end":27,"line_start":1,"line_end":1,"column_start":5,"column_end":28},"ref_id":{"krate":14,"index":546}},{"kind":"Type","span":{"file_name":"src\\lib.rs","byte_start":29,"byte_end":47,"line_start":1,"line_end":1,"column_start":30,"column_end":48},"ref_id":{"krate":14,"index":546}},{"kind":"Type","span":{"file_name":"src\\lib.rs","byte_start":49,"byte_end":57,"line_start":1,"line_end":1,"column_start":50,"column_end":58},"ref_id":{"krate":14,"index":546}},{"kind":"Type","span":{"file_name":"src\\lib.rs","byte_start":4,"byte_end":27,"line_start":1,"line_end":1,"column_start":5,"column_end":28},"ref_id":{"krate":14,"index":1181}},{"kind":"Type","span":{"file_name":"src\\lib.rs","byte_start":29,"byte_end":47,"line_start":1,"line_end":1,"column_start":30,"column_end":48},"ref_id":{"krate":14,"index":1181}},{"kind":"Type","span":{"file_name":"src\\lib.rs","byte_start":49,"byte_end":57,"line_start":1,"line_end":1,"column_start":50,"column_end":58},"ref_id":{"krate":14,"index":1181}},{"kind":"Variable","span":{"file_name":"src\\lib.rs","byte_start":4,"byte_end":27,"line_start":1,"line_end":1,"column_start":5,"column_end":28},"ref_id":{"krate":14,"index":545}},{"kind":"Variable","span":{"file_name":"src\\lib.rs","byte_start":29,"byte_end":47,"line_start":1,"line_end":1,"column_start":30,"column_end":48},"ref_id":{"krate":14,"index":545}},{"kind":"Variable","span":{"file_name":"src\\lib.rs","byte_start":49,"byte_end":57,"line_start":1,"line_end":1,"column_start":50,"column_end":58},"ref_id":{"krate":14,"index":545}},{"kind":"Type","span":{"file_name":"src\\lib.rs","byte_start":161,"byte_end":184,"line_start":4,"line_end":4,"column_start":5,"column_end":28},"ref_id":{"krate":14,"index":1259}},{"kind":"Type","span":{"file_name":"src\\lib.rs","byte_start":186,"byte_end":204,"line_start":4,"line_end":4,"column_start":30,"column_end":48},"ref_id":{"krate":14,"index":1259}},{"kind":"Type","span":{"file_name":"src\\lib.rs","byte_start":161,"byte_end":184,"line_start":4,"line_end":4,"column_start":5,"column_end":28},"ref_id":{"krate":14,"index":569}},{"kind":"Type","span":{"file_name":"src\\lib.rs","byte_start":186,"byte_end":204,"line_start":4,"line_end":4,"column_start":30,"column_end":48},"ref_id":{"krate":14,"index":569}},{"kind":"Mod","span":{"file_name":"src\\lib.rs","byte_start":228,"byte_end":251,"line_start":5,"line_end":5,"column_start":5,"column_end":28},"ref_id":{"krate":14,"index":0}},{"kind":"Mod","span":{"file_name":"src\\lib.rs","byte_start":253,"byte_end":271,"line_start":5,"line_end":5,"column_start":30,"column_end":48},"ref_id":{"krate":14,"index":208}},{"kind":"Mod","span":{"file_name":"src\\lib.rs","byte_start":295,"byte_end":303,"line_start":6,"line_end":6,"column_start":5,"column_end":13},"ref_id":{"krate":17,"index":0}},{"kind":"Type","span":{"file_name":"src\\lib.rs","byte_start":295,"byte_end":303,"line_start":6,"line_end":6,"column_start":5,"column_end":13},"ref_id":{"krate":17,"index":97}},{"kind":"Type","span":{"file_name":"src\\lib.rs","byte_start":305,"byte_end":310,"line_start":6,"line_end":6,"column_start":15,"column_end":20},"ref_id":{"krate":17,"index":97}},{"kind":"Type","span":{"file_name":"src\\lib.rs","byte_start":295,"byte_end":303,"line_start":6,"line_end":6,"column_start":5,"column_end":13},"ref_id":{"krate":17,"index":344}},{"kind":"Type","span":{"file_name":"src\\lib.rs","byte_start":305,"byte_end":310,"line_start":6,"line_end":6,"column_start":15,"column_end":20},"ref_id":{"krate":17,"index":344}},{"kind":"Mod","span":{"file_name":"src\\lib.rs","byte_start":358,"byte_end":366,"line_start":7,"line_end":7,"column_start":5,"column_end":13},"ref_id":{"krate":15,"index":0}},{"kind":"Mod","span":{"file_name":"src\\lib.rs","byte_start":368,"byte_end":379,"line_start":7,"line_end":7,"column_start":15,"column_end":26},"ref_id":{"krate":15,"index":34}},{"kind":"Mod","span":{"file_name":"src\\lib.rs","byte_start":397,"byte_end":405,"line_start":8,"line_end":8,"column_start":5,"column_end":13},"ref_id":{"krate":15,"index":0}},{"kind":"Mod","span":{"file_name":"src\\lib.rs","byte_start":407,"byte_end":417,"line_start":8,"line_end":8,"column_start":15,"column_end":25},"ref_id":{"krate":15,"index":1188}},{"kind":"Mod","span":{"file_name":"src\\lib.rs","byte_start":439,"byte_end":447,"line_start":9,"line_end":9,"column_start":5,"column_end":13},"ref_id":{"krate":15,"index":739}},{"kind":"Type","span":{"file_name":"src\\lib.rs","byte_start":439,"byte_end":447,"line_start":9,"line_end":9,"column_start":5,"column_end":13},"ref_id":{"krate":22,"index":514}},{"kind":"Type","span":{"file_name":"src\\lib.rs","byte_start":439,"byte_end":447,"line_start":9,"line_end":9,"column_start":5,"column_end":13},"ref_id":{"krate":15,"index":1746}},{"kind":"Type","span":{"file_name":"src\\lib.rs","byte_start":439,"byte_end":447,"line_start":9,"line_end":9,"column_start":5,"column_end":13},"ref_id":{"krate":15,"index":1133}},{"kind":"Mod","span":{"file_name":"src\\lib.rs","byte_start":550,"byte_end":553,"line_start":12,"line_end":12,"column_start":5,"column_end":8},"ref_id":{"krate":1,"index":0}},{"kind":"Mod","span":{"file_name":"src\\lib.rs","byte_start":555,"byte_end":566,"line_start":12,"line_end":12,"column_start":10,"column_end":21},"ref_id":{"krate":1,"index":989}},{"kind":"Type","span":{"file_name":"src\\lib.rs","byte_start":581,"byte_end":589,"line_start":13,"line_end":13,"column_start":5,"column_end":13},"ref_id":{"krate":20,"index":1984}},{"kind":"Type","span":{"file_name":"src\\lib.rs","byte_start":591,"byte_end":596,"line_start":13,"line_end":13,"column_start":15,"column_end":20},"ref_id":{"krate":20,"index":1984}},{"kind":"Type","span":{"file_name":"src\\lib.rs","byte_start":581,"byte_end":589,"line_start":13,"line_end":13,"column_start":5,"column_end":13},"ref_id":{"krate":20,"index":1448}},{"kind":"Type","span":{"file_name":"src\\lib.rs","byte_start":591,"byte_end":596,"line_start":13,"line_end":13,"column_start":15,"column_end":20},"ref_id":{"krate":20,"index":1448}},{"kind":"Type","span":{"file_name":"src\\lib.rs","byte_start":628,"byte_end":631,"line_start":14,"line_end":14,"column_start":5,"column_end":8},"ref_id":{"krate":2,"index":2898}},{"kind":"Type","span":{"file_name":"src\\lib.rs","byte_start":633,"byte_end":640,"line_start":14,"line_end":14,"column_start":10,"column_end":17},"ref_id":{"krate":2,"index":2898}},{"kind":"Type","span":{"file_name":"src\\lib.rs","byte_start":628,"byte_end":631,"line_start":14,"line_end":14,"column_start":5,"column_end":8},"ref_id":{"krate":2,"index":2902}},{"kind":"Type","span":{"file_name":"src\\lib.rs","byte_start":633,"byte_end":640,"line_start":14,"line_end":14,"column_start":10,"column_end":17},"ref_id":{"krate":2,"index":2902}}],"macro_refs":[],"relations":[]}